KinMSGUI/GUI.py
KinMSGUI/GUIFunctions.py
KinMSGUI/KinMS.py
KinMSGUI/__init__.py
KinMSGUI/makebeam.py
KinMSGUI/sauron_colormap.py
KinMSGUI-1.0.3.dist-info/METADATA
KinMSGUI-1.0.3.dist-info/RECORD
KinMSGUI-1.0.3.dist-info/WHEEL
KinMSGUI-1.0.3.dist-info/top_level.txt
