Metadata-Version: 2.1
Name: KinMSGUI
Version: 1.0.3
Summary: GUI Interface for KinMS software
Home-page: https://github.com/TristanBurman/KinMSGUI
Author: Tristan Burman
Author-email: BurmanT@cardiff.ac.uk
License: UNKNOWN
Platform: UNKNOWN
Classifier: Programming Language :: Python :: 3
Classifier: License :: OSI Approved :: MIT License
